lightscope/__main__.py
lightscope/lightscope.py
lightscope/lightscope_core.py
lightscope-0.0.100.dist-info/licenses/LICENSE
lightscope-0.0.100.dist-info/METADATA
lightscope-0.0.100.dist-info/WHEEL
lightscope-0.0.100.dist-info/entry_points.txt
lightscope-0.0.100.dist-info/top_level.txt
lightscope-0.0.100.dist-info/RECORD
